LICENSE.txt
README.md
setup.cfg
setup.py
gigaanalysis/__init__.py
gigaanalysis/const.py
gigaanalysis/contour.py
gigaanalysis/data.py
gigaanalysis/diglock.py
gigaanalysis/dset.py
gigaanalysis/fit.py
gigaanalysis/heatc.py
gigaanalysis/highfield.py
gigaanalysis/htsc.py
gigaanalysis/magnetism.py
gigaanalysis/mfunc.py
gigaanalysis/mfunc_fft.py
gigaanalysis/mfunc_make.py
gigaanalysis/mfunc_trans.py
gigaanalysis/mfunc_ufunc.py
gigaanalysis/parse.py
gigaanalysis/qo.py
gigaanalysis.egg-info/PKG-INFO
gigaanalysis.egg-info/SOURCES.txt
gigaanalysis.egg-info/dependency_links.txt
gigaanalysis.egg-info/requires.txt
gigaanalysis.egg-info/top_level.txt