Metadata-Version: 2.1
Name: gigaanalysis
Version: 0.3.2
Summary: A toolbox for processing data that can be expressed as a dependent and independent variable.
Home-page: https://github.com/alexeatscake/gigaanalysis
Author: Alex Hickey
Author-email: alexander.john.hickey@gmail.com
License: BSD 3-Clause License
Project-URL: Source Code, https://github.com/alexeatscake/gigaanalysis
Keywords: magnets, SdH, dHvA, magnetic, quantum, oscillations,,superconductor, quantum oscillations, EMFL, digital lock in, bsd-3-clause
Platform: UNKNOWN
Classifier: Intended Audience :: Science/Research
Classifier: Programming Language :: Python :: 3
Classifier: Programming Language :: Python :: 3.7
Classifier: Programming Language :: Python :: 3.8
Classifier: Programming Language :: Python :: 3.9
Classifier: Topic :: Scientific/Engineering
Classifier: Topic :: Scientific/Engineering :: Physics
Requires-Python: >=3.7
Provides-Extra: dev
License-File: LICENSE.txt
